vegetable/__init__.py
vegetable/column.py
vegetable/format.py
vegetable/highlight.py
vegetable/output/__init__.py
vegetable/output/delimited.py
vegetable/output/json.py
vegetable/output/table.py
vegetable/output/yaml.py
vegetable/tests/test_column.py
vegetable/tests/test_delimited.py
vegetable/tests/test_format.py
vegetable-1.1.1.dist-info/LICENSE
vegetable-1.1.1.dist-info/WHEEL
vegetable-1.1.1.dist-info/METADATA
vegetable-1.1.1.dist-info/RECORD
