Metadata-Version: 2.3
Name: vegetable
Version: 1.1.1
Summary: Tabular data formatter with column types/formatting options and other features.
Author-email: Mouse <mousefad@googlemail.com>
Classifier: License :: OSI Approved :: MIT License
Requires-Dist: colored
Requires-Dist: PyYAML
Project-URL: Home, https://github.com/mousefad/python-vegetable
